i7api/__init__.py
i7api/base.py
i7api-3.0.0.dist-info/METADATA
i7api-3.0.0.dist-info/WHEEL
i7api-3.0.0.dist-info/top_level.txt
i7api-3.0.0.dist-info/RECORD
