Metadata-Version: 2.1
Name: i7api
Version: 3.0.0
Summary: API Wrapper for i7StorageEngine
Author: Ojas Gupta
Classifier: Programming Language :: Python :: 3
Classifier: License :: OSI Approved :: MIT License
Classifier: Operating System :: OS Independent
Requires-Python: >=3.6
Requires-Dist: requests
